LICENSE.TXT
MANIFEST.in
README.md
__main__.py
requirements.txt
setup.py
version.txt
docs/requirements.txt
qt4i/__init__.py
qt4i/app.py
qt4i/cmds.py
qt4i/device.py
qt4i/exceptions.py
qt4i/icontrols.py
qt4i/itestcase.py
qt4i/qpath.py
qt4i/util.py
qt4i/version.py
qt4i/web.py
qt4i.egg-info/PKG-INFO
qt4i.egg-info/SOURCES.txt
qt4i.egg-info/dependency_links.txt
qt4i.egg-info/entry_points.txt
qt4i.egg-info/requires.txt
qt4i.egg-info/top_level.txt
qt4i/driver/__init__.py
qt4i/driver/driverserver.py
qt4i/driver/host.py
qt4i/driver/rpc.py
qt4i/driver/instruments/__init__.py
qt4i/driver/instruments/ins.py
qt4i/driver/instruments/uia.py
qt4i/driver/instruments/internal/__init__.py
qt4i/driver/instruments/internal/_api.js
qt4i/driver/instruments/internal/_bootstrap.js
qt4i/driver/instruments/internal/_cmd_fetch_delegate.py
qt4i/driver/instruments/internal/_command.py
qt4i/driver/instruments/internal/_jsonp.py
qt4i/driver/instruments/internal/_lib.js
qt4i/driver/instruments/internal/_timer.py
qt4i/driver/instruments/internal/_xcode.py
qt4i/driver/instruments/internal/instruments.py
qt4i/driver/instruments/internal/_tracetemplate/activity_monitor.tracetemplate
qt4i/driver/instruments/internal/_tracetemplate/ca_timeprofiler.tracetemplate
qt4i/driver/instruments/internal/_tracetemplate/core_animation.tracetemplate
qt4i/driver/instruments/internal/_tracetemplate/io_activity.tracetemplate
qt4i/driver/tools/__init__.py
qt4i/driver/tools/dt.py
qt4i/driver/tools/logger.py
qt4i/driver/tools/mobiledevice.py
qt4i/driver/tools/rvictl.py
qt4i/driver/tools/sched.py
qt4i/driver/tools/screencapture.py
qt4i/driver/util/__init__.py
qt4i/driver/util/_args.py
qt4i/driver/util/_files.py
qt4i/driver/util/_process.py
qt4i/driver/util/_task.py
qt4i/driver/util/modalmap.py
qt4i/driver/util/uimap.py
qt4i/driver/web/__init__.py
qt4i/driver/web/web.py
qt4i/driver/web/wkrdp.py
qt4i/driver/xctest/__init__.py
qt4i/driver/xctest/agent.py
qt4i/driver/xctest/wda.py
qt4i/driver/xctest/bin/iphonesimulator-10.xctestrun
qt4i/driver/xctest/bin/iphonesimulator-11.xctestrun
qt4i/driver/xctest/bin/iphonesimulator-9.xctestrun
qt4i/driver/xctest/webdriverclient/__init__.py
