Metadata-Version: 2.1
Name: qt4i
Version: 3.5.1
Summary: QTA driver for iOS app
Home-page: https://github.com/Tencent/QT4i
Author: Tencent
License: Copyright(c)2010-2018 Tencent All Rights Reserved. 
Project-URL: QT4i Documentation, https://qt4i.readthedocs.io/zh_CN/latest/
Platform: UNKNOWN
Classifier: Programming Language :: Python :: 2.7
Classifier: Programming Language :: Python :: 3.5
Classifier: Programming Language :: Python :: 3.6
Classifier: Programming Language :: Python :: 3.7
